CHANGES
LICENSE
README.rst
TODO
setup.cfg
setup.py
DesktopStreamer.egg-info/PKG-INFO
DesktopStreamer.egg-info/SOURCES.txt
DesktopStreamer.egg-info/dependency_links.txt
DesktopStreamer.egg-info/entry_points.txt
DesktopStreamer.egg-info/top_level.txt
data/StreamDesktop.desktop
data/desktopstreamer.png
data/desktopstreamer.svg
data/stream_desktop.sh
desktopstreamer/__init__.py
desktopstreamer/__main__.py
desktopstreamer/cli.py
desktopstreamer/desktopstreamer.py
desktopstreamer/gui.py