Metadata-Version: 1.0
Name: DesktopStreamer
Version: 0.6.1
Summary: Capture A/V from the desktop and stream it to the local network.
Home-page: https://github.com/brutus/Desktop-Streamer/
Author: Brutus [dmc]
Author-email: brutus.dmc@googlemail.com
License: GPLv3
Platform: UNKNOWN
